rcsssmj/__init__.py
rcsssmj/__main__.py
rcsssmj/agents.py
rcsssmj/mjutils.py
rcsssmj/server.py
rcsssmj/simulation.py
rcsssmj/simulation_interfaces.py
rcsssmj/agent/__init__.py
rcsssmj/agent/action.py
rcsssmj/agent/encoder.py
rcsssmj/agent/parser.py
rcsssmj/agent/perception.py
rcsssmj/agent/sim_agent.py
rcsssmj/communication/__init__.py
rcsssmj/communication/connection.py
rcsssmj/communication/tcp_lpm_connection.py
rcsssmj/games/__init__.py
rcsssmj/games/game.py
rcsssmj/games/teams.py
rcsssmj/games/soccer/__init__.py
rcsssmj/games/soccer/field.py
rcsssmj/games/soccer/game.py
rcsssmj/games/soccer/game_object.py
rcsssmj/games/soccer/game_state.py
rcsssmj/games/soccer/play_mode.py
rcsssmj/games/soccer/referee.py
rcsssmj/games/soccer/rules.py
rcsssmj/games/soccer/soccer_server.py
rcsssmj/games/soccer/soccer_sim.py
rcsssmj/games/soccer/soccer_sim_interfaces.py
rcsssmj/games/soccer/agent/__init__.py
rcsssmj/games/soccer/agent/action.py
rcsssmj/games/soccer/agent/parser.py
rcsssmj/games/soccer/agent/perception.py
rcsssmj/games/soccer/monitor/__init__.py
rcsssmj/games/soccer/monitor/command.py
rcsssmj/games/soccer/monitor/parser.py
rcsssmj/games/soccer/monitor/state.py
rcsssmj/monitor/__init__.py
rcsssmj/monitor/commands.py
rcsssmj/monitor/mujoco_monitor.py
rcsssmj/monitor/parser.py
rcsssmj/monitor/sim_monitor.py
rcsssmj/monitor/state.py
rcsssmj/resources/__init__.py
rcsssmj/resources/spec_provider.py
rcsssmj/resources/environments/soccer/world.xml
rcsssmj/resources/environments/soccer/assets/back.png
rcsssmj/resources/environments/soccer/assets/down.png
rcsssmj/resources/environments/soccer/assets/front.png
rcsssmj/resources/environments/soccer/assets/left.png
rcsssmj/resources/environments/soccer/assets/pitch_nologo_l.png
rcsssmj/resources/environments/soccer/assets/right.png
rcsssmj/resources/environments/soccer/assets/up.png
rcsssmj/resources/robots/README.md
rcsssmj/resources/robots/T1/LICENSE
rcsssmj/resources/robots/T1/robot.xml
rcsssmj-0.1.0.dist-info/METADATA
rcsssmj-0.1.0.dist-info/WHEEL
rcsssmj-0.1.0.dist-info/entry_points.txt
rcsssmj-0.1.0.dist-info/licenses/AUTHORS.md
rcsssmj-0.1.0.dist-info/licenses/LICENSE
rcsssmj-0.1.0.dist-info/licenses/src/rcsssmj/resources/robots/T1/LICENSE
rcsssmj-0.1.0.dist-info/licenses/src/rcsssmj/resources/robots/ant/LICENSE
rcsssmj-0.1.0.dist-info/RECORD
