Metadata-Version: 2.4
Name: rcsssmj
Version: 0.1.0
Summary: MuJoCo based RoboCup Soccer Simulation Server
Project-URL: Homepage, https://gitlab.com/robocup-sim/rcssservermj
Project-URL: Documentation, https://robocup-sim.gitlab.io/rcssservermj/
Project-URL: Repository, https://gitlab.com/robocup-sim/rcssservermj/-/tree/master
Project-URL: Issues, https://gitlab.com/robocup-sim/rcssservermj/-/issues
Author-email: Stefan Glaser <glaser.stefan@gmx.net>, Nico Bohlinger <nico.bohlinger@gmail.com>, Hannes Braun <hannes@hannesbraun.net>
Maintainer-email: Stefan Glaser <glaser.stefan@gmx.net>
License-Expression: MIT
License-File: AUTHORS.md
License-File: LICENSE
License-File: src/rcsssmj/resources/robots/T1/LICENSE
License-File: src/rcsssmj/resources/robots/ant/LICENSE
Keywords: AI,Competition,Humanoid,Machine Learning,MuJoCo,RoboCup,Robot,Simulation,Soccer
Classifier: Development Status :: 3 - Alpha
Classifier: Intended Audience :: Developers
Classifier: Intended Audience :: Science/Research
Classifier: License :: OSI Approved :: MIT License
Classifier: Natural Language :: English
Classifier: Programming Language :: Python
Classifier: Topic :: Scientific/Engineering
Classifier: Topic :: Scientific/Engineering :: Artificial Intelligence
Classifier: Topic :: Scientific/Engineering :: Physics
Classifier: Topic :: Software Development
Classifier: Typing :: Typed
Requires-Python: >=3.10
Requires-Dist: mujoco==3.4.0
Requires-Dist: numpy
Provides-Extra: ogl
Requires-Dist: pyopengl; extra == 'ogl'
